rocketpdf/__init__.py
rocketpdf/doc_parser/__init__.py
rocketpdf/doc_parser/doc_parser.py
rocketpdf/doc_parser/utils/__init__.py
rocketpdf/doc_parser/utils/decorator.py
rocketpdf/doc_parser/utils/system.py
rocketpdf/doc_parser/utils/types.py
rocketpdf/rocketpdf.py
rocketpdf-0.1.4.dist-info/entry_points.txt
rocketpdf-0.1.4.dist-info/LICENSE
rocketpdf-0.1.4.dist-info/METADATA
rocketpdf-0.1.4.dist-info/WHEEL
rocketpdf-0.1.4.dist-info/RECORD
